{
  "login": "Poonam5",
  "id": 683799,
  "avatar_url": "https://avatars0.githubusercontent.com/u/683799?v=4",
  "gravatar_id": "",
  "url": "https://api.github.com/users/Shashikant86",
  "html_url": "https://github.com/Shashikant86",
  "followers_url": "https://api.github.com/users/Shashikant86/followers",
  "following_url": "https://api.github.com/users/Shashikant86/following{/other_user}",
  "gists_url": "https://api.github.com/users/Shashikant86/gists{/gist_id}",
  "starred_url": "https://api.github.com/users/Shashikant86/starred{/owner}{/repo}",
  "subscriptions_url": "https://api.github.com/users/Shashikant86/subscriptions",
  "organizations_url": "https://api.github.com/users/Shashikant86/orgs",
  "repos_url": "https://api.github.com/users/Shashikant86/repos",
  "events_url": "https://api.github.com/users/Shashikant86/events{/privacy}",
  "received_events_url": "https://api.github.com/users/Shashikant86/received_events",
  "type": "User",
  "site_admin": false,
  "name": "Poonam",
  "company": "@AOL, @BBC, @PhotoBox",
  "blog": "http://shashikantjagtap.net",
  "location": "London",
  "email": null,
  "hireable": null,
  "bio": "Author of BDDfire & XCFit. DevOps Automation iOS Swift PHP Ruby Development. CI&CD[Jenkins, Docker, AWS, Xcode Server] BDD[Cucumber Behat Cucumberish, Fitnesse]",
  "public_repos": 112,
  "public_gists": 1,
  "followers": 108,
  "following": 52,
  "created_at": "2011-03-22T12:39:11Z",
  "updated_at": "2017-10-05T14:32:54Z"
}
